tuplelist_virumoru/__init__.py
tuplelist_virumoru-0.0.1.dist-info/METADATA
tuplelist_virumoru-0.0.1.dist-info/WHEEL
tuplelist_virumoru-0.0.1.dist-info/licenses/LICENSE
tuplelist_virumoru-0.0.1.dist-info/RECORD
