Metadata-Version: 2.1
Name: TupleList_virumoru
Version: 0.0.1
Summary: A subclass of 'list' only allowing 'tuple's as its items
Project-URL: Homepage, https://github.com/virumoru/TupleList
Project-URL: Bug Tracker, https://github.com/virumoru/TupleList/issues
Author: virumoru
License: This is free and unencumbered software released into the public domain.
Classifier: License :: OSI Approved :: The Unlicense (Unlicense)
Classifier: Operating System :: OS Independent
Classifier: Programming Language :: Python :: 3
Requires-Python: >=3.9
